adaone_utils-0.0.6.dist-info/METADATA
adaone_utils-0.0.6.dist-info/WHEEL
adaone_utils-0.0.6.dist-info/licenses/LICENSE
adaone_utils/__init__.py
adaone_utils/_internal.cp312-win_amd64.pyd
adaone_utils/_internal.pyi
adaone_utils/py.typed
adaone_utils-0.0.6.dist-info/RECORD
