Metadata-Version: 2.4
Name: adaone-utils
Version: 0.0.6
Classifier: Programming Language :: Rust
Classifier: Programming Language :: Python :: Implementation :: CPython
Classifier: Programming Language :: Python :: Implementation :: PyPy
Requires-Dist: maturin>=1.8.2
Requires-Dist: polars[pyarrow,numpy]>=1.22.0,!=1.32.*
Requires-Dist: numpy>=2.2.3
Requires-Dist: pytest>=8.3.4
Requires-Dist: jupyter ; extra == 'dev'
Requires-Dist: pytest ; extra == 'test'
Requires-Dist: mypy ; extra == 'test'
Provides-Extra: dev
Provides-Extra: test
License-File: LICENSE
Summary: Utilities for working with AdaOne toolpaths
Keywords: adaone,adaxis,toolpath,slicing,3d-printing,robotics
Author-email: CEAD Group <software@ceadgroup.com>
License-Expression: MIT
Requires-Python: >=3.12
Project-URL: Homepage, https://github.com/CEAD-group/adaone-utils
Project-URL: Repository, https://github.com/CEAD-group/adaone-utils.git
Project-URL: Documentation, https://github.com/CEAD-group/adaone-utils/blob/main/README.md
